b_cfn_opensearch_index/__init__.py
b_cfn_opensearch_index/function.py
b_cfn_opensearch_index/resource.py
b_cfn_opensearch_index/source/__init__.py
b_cfn_opensearch_index/source/main/__init__.py
b_cfn_opensearch_index/source/main/action.py
b_cfn_opensearch_index/source/main/index.py
b_cfn_opensearch_index/source/main/opensearch_index_id.py
b_cfn_opensearch_index_layer/__init__.py
b_cfn_opensearch_index_layer/layer.py
b_cfn_opensearch_index_layer/opensearch_client.py
b_cfn_opensearch_index_tests/integration/__init__.py
b_cfn_opensearch_index_tests/integration/app.py
b_cfn_opensearch_index_tests/integration/conftest.py
b_cfn_opensearch_index_tests/integration/infra_create.py
b_cfn_opensearch_index_tests/integration/infra_destroy.py
b_cfn_opensearch_index_tests/integration/manager.py
b_cfn_opensearch_index_tests/integration/fixtures/__init__.py
b_cfn_opensearch_index_tests/integration/fixtures/documents.py
b_cfn_opensearch_index_tests/integration/fixtures/generate_documents.py
b_cfn_opensearch_index_tests/integration/fixtures/opensearch_client.py
b_cfn_opensearch_index_tests/integration/infrastructure/__init__.py
b_cfn_opensearch_index_tests/integration/infrastructure/main_stack.py
b_cfn_opensearch_index_tests/integration/infrastructure/opensearch_domain_stack.py
b_cfn_opensearch_index_tests/integration/infrastructure/opensearch_index_resource.py
b_cfn_opensearch_index_tests/integration/infrastructure/functions/__init__.py
b_cfn_opensearch_index_tests/integration/infrastructure/functions/function1.py
b_cfn_opensearch_index_tests/integration/infrastructure/functions/source/__init__.py
b_cfn_opensearch_index_tests/integration/infrastructure/functions/source/index.py
b_cfn_opensearch_index_tests/integration/tests/__init__.py
b_cfn_opensearch_index_tests/integration/tests/dummy_index.py
b_cfn_opensearch_index_tests/integration/tests/test_opensearch_index_layer.py
b_cfn_opensearch_index_tests/integration/tests/test_resource_opensearch_index.py
b_cfn_opensearch_index-0.0.3.dist-info/LICENSE
b_cfn_opensearch_index-0.0.3.dist-info/METADATA
b_cfn_opensearch_index-0.0.3.dist-info/WHEEL
b_cfn_opensearch_index-0.0.3.dist-info/top_level.txt
b_cfn_opensearch_index-0.0.3.dist-info/RECORD
