Metadata-Version: 2.1
Name: b-cfn-opensearch-index
Version: 0.0.3
Summary: AWS CDK based custom resource that manages an Opensearch index.
Home-page: https://github.com/Biomapas/B.CfnOpenSearchIndex.git
Author: Gediminas Kazlauskas
Author-email: gediminas.kazlauskas@biomapas.com
License: Apache License 2.0
Keywords: AWS CDK OpenSearch Index
Platform: UNKNOWN
Classifier: Programming Language :: Python :: 3
Classifier: Operating System :: OS Independent
Requires-Dist: aws-cdk.core (<2.0.0,>=1.159.0)
Requires-Dist: aws-cdk.aws-lambda (<2.0.0,>=1.159.0)
Requires-Dist: aws-cdk.aws-opensearchservice (<2.0.0,>=1.159.0)
Requires-Dist: b-aws-cf-response (<1.0.0,>=0.0.1)
Requires-Dist: b-aws-testing-framework (<1.0.0,>=0.6.0)
Requires-Dist: b-cfn-lambda-layer (<3.0.0,>=2.3.0)
Requires-Dist: opensearch-py (<2.0.0,>=1.0.0)
Requires-Dist: requests-aws4auth (<2.0.0,>=1.1.1)
Requires-Dist: Faker (<11.0.0,>=10.0.0)
